bot_whatsapp/__init__.py
bot_whatsapp/bot.py
bot_whatsapp/constants.py
bot_whatsapp/filters.py
bot_whatsapp/handler.py
bot_whatsapp/models.py
bot_whatsapp-0.0.6.dist-info/LICENSE
bot_whatsapp-0.0.6.dist-info/METADATA
bot_whatsapp-0.0.6.dist-info/WHEEL
bot_whatsapp-0.0.6.dist-info/RECORD
