Metadata-Version: 2.1
Name: bot-whatsapp
Version: 0.0.6
Summary: python-telegram-bot for WhatsApp
License: Apache 2.0
Author: piEsposito
Author-email: piero.skywalker@gmail.com
Requires-Python: >=3.12,<4.0
Classifier: License :: Other/Proprietary License
Classifier: Programming Language :: Python :: 3
Classifier: Programming Language :: Python :: 3.12
Requires-Dist: aiohttp (>=3.9.5,<4.0.0)
Requires-Dist: fastapi (>=0.111.0,<0.112.0)
Requires-Dist: pydantic (>=2.7.3,<3.0.0)
Requires-Dist: requests (>=2.32.3,<3.0.0)
Requires-Dist: uvicorn (>=0.30.1,<0.31.0)
